<odoo>
    <data noupdate="1">
        <record id="ir_cron_get_books_cali" model="ir.cron">
            <field name="name">Get calificaciones</field>
            <field name="model_id" ref="model_app_gradebook_student"/>
            <field name="state">code</field>
            <field name="code">model.action_get_books()</field>
            <field name="interval_number">12</field>
            <field name="interval_type">hours</field>
            <field name="numbercall">-1</field>
            <field name="doall" eval="False"/>
        </record>
    </data>
</odoo>
